thunter/__init__.py
thunter/analyzer.py
thunter/constants.py
thunter/db.py
thunter/parser.py
thunter/settings.py
thunter/task_hunter.py
thunter/time.py
thunter/cli/__init__.py
thunter/cli/analyze.py
thunter/cli/cli.py
thunter/cli/create.py
thunter/cli/db.py
thunter/cli/edit.py
thunter/cli/estimate.py
thunter/cli/finish.py
thunter/cli/init.py
thunter/cli/ls.py
thunter/cli/restart.py
thunter/cli/rm.py
thunter/cli/show.py
thunter/cli/stop.py
thunter/cli/workon.py
thunter/models/__init__.py
thunter/models/task.py
thunter/models/task_history_record.py
thunter/tests/__init__.py
thunter/tests/test_database_fixture.sql
thunter/tests/test_db.py
thunter/tests/test_task_analyzer.py
thunter/tests/test_task_hunter.py
thunter/tests/test_task_parser.py
thunter/tests/test_cli/__init__.py
thunter/tests/test_cli/test_create.py
thunter/tests/test_cli/test_estimate.py
thunter/tests/test_cli/test_finish.py
thunter/tests/test_cli/test_list.py
thunter/tests/test_cli/test_main_callback.py
thunter/tests/test_cli/test_restart.py
thunter/tests/test_cli/test_rm.py
thunter/tests/test_cli/test_show.py
thunter/tests/test_cli/test_stop.py
thunter/tests/test_cli/test_workon.py
thunter/tests/test_models/__init__.py
thunter/tests/test_models/test_task.py
thunter/tests/test_models/test_task_history_record.py
thunter-0.2.1.dist-info/METADATA
thunter-0.2.1.dist-info/WHEEL
thunter-0.2.1.dist-info/entry_points.txt
thunter-0.2.1.dist-info/licenses/LICENCE.txt
thunter-0.2.1.dist-info/RECORD
