Metadata-Version: 2.4
Name: thunter
Version: 0.2.1
Summary: A CLI To Do list w/ time tracking.
Project-URL: Issues, https://github.com/AlejandroFrias/thunter/issues
Project-URL: Source, https://github.com/AlejandroFrias/thunter
Author-email: Alejandro Frias <joker454@gmail.com>
Maintainer-email: Alejandro Frias <joker454@gmail.com>
License-Expression: MIT
License-File: LICENCE.txt
Keywords: cli,task,todo,tracking
Classifier: Development Status :: 3 - Alpha
Classifier: Environment :: Console
Classifier: Intended Audience :: Developers
Classifier: Programming Language :: Python :: 3
Requires-Python: >=3.10
Requires-Dist: pandas>=2.3.1
Requires-Dist: pyparsing>=3.2.3
Requires-Dist: rich>=14.1.0
Requires-Dist: typer>=0.16.1
